{
    "zone": "IT-SAR",
    "temporalGranularity": "monthly",
    "unit": "MWh",
    "data": [
        {
            "datetime": "2022-01-01T00:00:00.000Z",
            "updatedAt": "2026-02-07T23:00:25.543Z",
            "estimationMethod": "MEASURED",
            "value": 310940
        },
        {
            "datetime": "2022-02-01T00:00:00.000Z",
            "updatedAt": "2026-02-01T07:23:33.794Z",
            "estimationMethod": "MEASURED",
            "value": 169254
        },
        {
            "datetime": "2022-03-01T00:00:00.000Z",
            "updatedAt": "2026-02-01T07:23:33.794Z",
            "estimationMethod": "MEASURED",
            "value": 189443
        },
        {
            "datetime": "2022-04-01T00:00:00.000Z",
            "updatedAt": "2026-02-01T07:23:33.794Z",
            "estimationMethod": "MEASURED",
            "value": 179912
        },
        {
            "datetime": "2022-05-01T00:00:00.000Z",
            "updatedAt": "2026-02-01T07:23:33.794Z",
            "estimationMethod": "MEASURED",
            "value": 275752
        },
        {
            "datetime": "2022-06-01T00:00:00.000Z",
            "updatedAt": "2026-02-01T07:23:33.794Z",
            "estimationMethod": "MEASURED",
            "value": 290293
        },
        {
            "datetime": "2022-07-01T00:00:00.000Z",
            "updatedAt": "2026-02-01T07:23:33.794Z",
            "estimationMethod": "MEASURED",
            "value": 282769
        },
        {
            "datetime": "2022-08-01T00:00:00.000Z",
            "updatedAt": "2026-02-01T07:23:33.794Z",
            "estimationMethod": "MEASURED",
            "value": 298918
        },
        {
            "datetime": "2022-09-01T00:00:00.000Z",
            "updatedAt": "2026-02-01T07:23:33.794Z",
            "estimationMethod": "MEASURED",
            "value": 246834
        },
        {
            "datetime": "2022-10-01T00:00:00.000Z",
            "updatedAt": "2026-02-01T07:23:33.794Z",
            "estimationMethod": "MEASURED",
            "value": 234273
        },
        {
            "datetime": "2022-11-01T00:00:00.000Z",
            "updatedAt": "2026-02-01T07:23:33.794Z",
            "estimationMethod": "MEASURED",
            "value": 221677
        },
        {
            "datetime": "2022-12-01T00:00:00.000Z",
            "updatedAt": "2026-02-01T07:23:33.794Z",
            "estimationMethod": "MEASURED",
            "value": 236780
        }
    ],
    "source": "gas",
    "aggregationPeriod": "monthly"
}