{
    "zone": "US-NW-BPAT",
    "temporalGranularity": "monthly",
    "unit": "MWh",
    "data": [
        {
            "datetime": "2022-01-01T00:00:00.000Z",
            "updatedAt": "2026-02-07T23:00:25.543Z",
            "estimationMethod": "MEASURED",
            "value": 3925
        },
        {
            "datetime": "2022-02-01T00:00:00.000Z",
            "updatedAt": "2026-02-01T07:23:33.794Z",
            "estimationMethod": "MEASURED",
            "value": 7245
        },
        {
            "datetime": "2022-03-01T00:00:00.000Z",
            "updatedAt": "2026-02-01T07:23:33.794Z",
            "estimationMethod": "MEASURED",
            "value": 9969
        },
        {
            "datetime": "2022-04-01T00:00:00.000Z",
            "updatedAt": "2026-02-01T07:23:33.794Z",
            "estimationMethod": "MEASURED",
            "value": 22278
        },
        {
            "datetime": "2022-05-01T00:00:00.000Z",
            "updatedAt": "2026-02-01T07:23:33.794Z",
            "estimationMethod": "MEASURED",
            "value": 15210
        },
        {
            "datetime": "2022-06-01T00:00:00.000Z",
            "updatedAt": "2026-02-01T07:23:33.794Z",
            "estimationMethod": "MEASURED",
            "value": 6944
        },
        {
            "datetime": "2022-07-01T00:00:00.000Z",
            "updatedAt": "2026-01-27T15:25:10.819Z",
            "estimationMethod": "MEASURED",
            "value": 11109
        },
        {
            "datetime": "2022-08-01T00:00:00.000Z",
            "updatedAt": "2026-02-01T07:23:33.794Z",
            "estimationMethod": "MEASURED",
            "value": 10850
        },
        {
            "datetime": "2022-09-01T00:00:00.000Z",
            "updatedAt": "2026-01-27T15:25:10.819Z",
            "estimationMethod": "MEASURED",
            "value": 5432
        },
        {
            "datetime": "2022-10-01T00:00:00.000Z",
            "updatedAt": "2026-02-01T07:23:33.794Z",
            "estimationMethod": "MEASURED",
            "value": 10106
        },
        {
            "datetime": "2022-11-01T00:00:00.000Z",
            "updatedAt": "2026-02-01T07:23:33.794Z",
            "estimationMethod": "MEASURED",
            "value": 17461
        },
        {
            "datetime": "2022-12-01T00:00:00.000Z",
            "updatedAt": "2026-02-01T07:23:33.794Z",
            "estimationMethod": "MEASURED",
            "value": 16701
        }
    ],
    "source": "solar",
    "aggregationPeriod": "monthly"
}