{
    "zone": "US-TEX-ERCO",
    "temporalGranularity": "monthly",
    "unit": "MWh",
    "data": [
        {
            "datetime": "2022-01-01T00:00:00.000Z",
            "updatedAt": "2026-02-07T23:00:25.543Z",
            "estimationMethod": "MEASURED",
            "value": 8468662
        },
        {
            "datetime": "2022-02-01T00:00:00.000Z",
            "updatedAt": "2026-01-27T15:25:10.819Z",
            "estimationMethod": "MEASURED",
            "value": 8326620
        },
        {
            "datetime": "2022-03-01T00:00:00.000Z",
            "updatedAt": "2026-01-27T15:25:10.819Z",
            "estimationMethod": "MEASURED",
            "value": 11054757
        },
        {
            "datetime": "2022-04-01T00:00:00.000Z",
            "updatedAt": "2026-01-27T15:25:10.819Z",
            "estimationMethod": "MEASURED",
            "value": 11761054
        },
        {
            "datetime": "2022-05-01T00:00:00.000Z",
            "updatedAt": "2026-01-27T15:25:10.819Z",
            "estimationMethod": "MEASURED",
            "value": 12493238
        },
        {
            "datetime": "2022-06-01T00:00:00.000Z",
            "updatedAt": "2026-01-27T15:25:10.819Z",
            "estimationMethod": "MEASURED",
            "value": 9825330
        },
        {
            "datetime": "2022-07-01T00:00:00.000Z",
            "updatedAt": "2026-01-27T15:25:10.819Z",
            "estimationMethod": "MEASURED",
            "value": 8841754
        },
        {
            "datetime": "2022-08-01T00:00:00.000Z",
            "updatedAt": "2026-01-27T15:25:10.819Z",
            "estimationMethod": "MEASURED",
            "value": 6422050
        },
        {
            "datetime": "2022-09-01T00:00:00.000Z",
            "updatedAt": "2026-01-27T15:25:10.819Z",
            "estimationMethod": "MEASURED",
            "value": 5767298
        },
        {
            "datetime": "2022-10-01T00:00:00.000Z",
            "updatedAt": "2026-01-27T15:25:10.819Z",
            "estimationMethod": "MEASURED",
            "value": 7414059
        },
        {
            "datetime": "2022-11-01T00:00:00.000Z",
            "updatedAt": "2026-01-27T15:25:10.819Z",
            "estimationMethod": "MEASURED",
            "value": 8999725
        },
        {
            "datetime": "2022-12-01T00:00:00.000Z",
            "updatedAt": "2026-02-01T07:23:33.794Z",
            "estimationMethod": "MEASURED",
            "value": 8517892
        }
    ],
    "source": "wind",
    "aggregationPeriod": "monthly"
}