{
    "zone": "SE",
    "temporalGranularity": "monthly",
    "unit": "MWh",
    "data": [
        {
            "datetime": "2022-01-01T00:00:00.000Z",
            "updatedAt": "2026-02-07T23:00:25.543Z",
            "estimationMethod": "MEASURED",
            "value": 5370038
        },
        {
            "datetime": "2022-02-01T00:00:00.000Z",
            "updatedAt": "2026-02-01T07:23:33.794Z",
            "estimationMethod": "MEASURED",
            "value": 5141152
        },
        {
            "datetime": "2022-03-01T00:00:00.000Z",
            "updatedAt": "2026-02-01T07:23:33.794Z",
            "estimationMethod": "MEASURED",
            "value": 5038308
        },
        {
            "datetime": "2022-04-01T00:00:00.000Z",
            "updatedAt": "2026-02-01T07:23:33.794Z",
            "estimationMethod": "MEASURED",
            "value": 4837739
        },
        {
            "datetime": "2022-05-01T00:00:00.000Z",
            "updatedAt": "2026-02-01T07:23:33.794Z",
            "estimationMethod": "MEASURED",
            "value": 4238943
        },
        {
            "datetime": "2022-06-01T00:00:00.000Z",
            "updatedAt": "2026-02-01T07:23:33.794Z",
            "estimationMethod": "MEASURED",
            "value": 4333194
        },
        {
            "datetime": "2022-07-01T00:00:00.000Z",
            "updatedAt": "2026-02-01T07:23:33.794Z",
            "estimationMethod": "MEASURED",
            "value": 3986370
        },
        {
            "datetime": "2022-08-01T00:00:00.000Z",
            "updatedAt": "2026-02-01T07:23:33.794Z",
            "estimationMethod": "MEASURED",
            "value": 4295953
        },
        {
            "datetime": "2022-09-01T00:00:00.000Z",
            "updatedAt": "2026-02-01T07:23:33.794Z",
            "estimationMethod": "MEASURED",
            "value": 4504681
        },
        {
            "datetime": "2022-10-01T00:00:00.000Z",
            "updatedAt": "2026-02-01T07:23:33.794Z",
            "estimationMethod": "MEASURED",
            "value": 3709910
        },
        {
            "datetime": "2022-11-01T00:00:00.000Z",
            "updatedAt": "2026-02-01T07:23:33.794Z",
            "estimationMethod": "MEASURED",
            "value": 5439403
        },
        {
            "datetime": "2022-12-01T00:00:00.000Z",
            "updatedAt": "2026-02-01T07:23:33.794Z",
            "estimationMethod": "MEASURED",
            "value": 6093302
        }
    ],
    "source": "hydro",
    "aggregationPeriod": "monthly"
}