{
    "zone": "ES-CN-FV",
    "temporalGranularity": "monthly",
    "unit": "MWh",
    "data": [
        {
            "datetime": "2022-01-01T00:00:00.000Z",
            "updatedAt": "2026-02-07T23:00:25.543Z",
            "estimationMethod": "MEASURED",
            "value": 7642
        },
        {
            "datetime": "2022-02-01T00:00:00.000Z",
            "updatedAt": "2026-01-27T15:25:10.819Z",
            "estimationMethod": "MEASURED",
            "value": 7045
        },
        {
            "datetime": "2022-03-01T00:00:00.000Z",
            "updatedAt": "2026-01-27T15:25:10.819Z",
            "estimationMethod": "MEASURED",
            "value": 8039
        },
        {
            "datetime": "2022-04-01T00:00:00.000Z",
            "updatedAt": "2026-01-27T15:25:10.819Z",
            "estimationMethod": "MEASURED",
            "value": 3870
        },
        {
            "datetime": "2022-05-01T00:00:00.000Z",
            "updatedAt": "2026-01-27T15:25:10.819Z",
            "estimationMethod": "MEASURED",
            "value": 6654
        },
        {
            "datetime": "2022-06-01T00:00:00.000Z",
            "updatedAt": "2026-01-27T15:25:10.819Z",
            "estimationMethod": "MEASURED",
            "value": 13185
        },
        {
            "datetime": "2022-07-01T00:00:00.000Z",
            "updatedAt": "2026-01-27T15:25:10.819Z",
            "estimationMethod": "MEASURED",
            "value": 15114
        },
        {
            "datetime": "2022-08-01T00:00:00.000Z",
            "updatedAt": "2026-01-27T15:25:10.819Z",
            "estimationMethod": "MEASURED",
            "value": 16120
        },
        {
            "datetime": "2022-09-01T00:00:00.000Z",
            "updatedAt": "2026-01-27T15:25:10.819Z",
            "estimationMethod": "MEASURED",
            "value": 13068
        },
        {
            "datetime": "2022-10-01T00:00:00.000Z",
            "updatedAt": "2026-01-27T15:25:10.819Z",
            "estimationMethod": "MEASURED",
            "value": 7853
        },
        {
            "datetime": "2022-11-01T00:00:00.000Z",
            "updatedAt": "2026-01-27T15:25:10.819Z",
            "estimationMethod": "MEASURED",
            "value": 9300
        },
        {
            "datetime": "2022-12-01T00:00:00.000Z",
            "updatedAt": "2026-01-27T15:25:10.819Z",
            "estimationMethod": "MEASURED",
            "value": 7548
        }
    ],
    "source": "wind",
    "aggregationPeriod": "monthly"
}