{
    "zone": "CN",
    "temporalGranularity": "monthly",
    "unit": "MWh",
    "data": [
        {
            "datetime": "2023-01-01T00:00:00.000Z",
            "updatedAt": "2026-02-09T20:20:37.719Z",
            "isEstimated": true,
            "estimationMethod": "ESTIMATED_GENERAL_PURPOSE_ZONE_MODEL",
            "value": 34559996
        },
        {
            "datetime": "2023-02-01T00:00:00.000Z",
            "updatedAt": "2026-02-01T07:23:33.961Z",
            "isEstimated": true,
            "estimationMethod": "ESTIMATED_GENERAL_PURPOSE_ZONE_MODEL",
            "value": 34359996
        },
        {
            "datetime": "2023-03-01T00:00:00.000Z",
            "updatedAt": "2026-02-01T07:23:33.961Z",
            "isEstimated": true,
            "estimationMethod": "ESTIMATED_GENERAL_PURPOSE_ZONE_MODEL",
            "value": 44580000
        },
        {
            "datetime": "2023-04-01T00:00:00.000Z",
            "updatedAt": "2026-02-01T07:23:33.961Z",
            "isEstimated": true,
            "estimationMethod": "ESTIMATED_GENERAL_PURPOSE_ZONE_MODEL",
            "value": 45710004
        },
        {
            "datetime": "2023-05-01T00:00:00.000Z",
            "updatedAt": "2026-02-01T07:23:33.961Z",
            "isEstimated": true,
            "estimationMethod": "ESTIMATED_GENERAL_PURPOSE_ZONE_MODEL",
            "value": 51130000
        },
        {
            "datetime": "2023-06-01T00:00:00.000Z",
            "updatedAt": "2026-02-01T07:23:33.961Z",
            "isEstimated": true,
            "estimationMethod": "ESTIMATED_GENERAL_PURPOSE_ZONE_MODEL",
            "value": 55950000
        },
        {
            "datetime": "2023-07-01T00:00:00.000Z",
            "updatedAt": "2026-02-01T07:23:33.961Z",
            "isEstimated": true,
            "estimationMethod": "ESTIMATED_GENERAL_PURPOSE_ZONE_MODEL",
            "value": 57799992
        },
        {
            "datetime": "2023-08-01T00:00:00.000Z",
            "updatedAt": "2026-02-01T07:23:33.961Z",
            "isEstimated": true,
            "estimationMethod": "ESTIMATED_GENERAL_PURPOSE_ZONE_MODEL",
            "value": 59240004
        },
        {
            "datetime": "2023-09-01T00:00:00.000Z",
            "updatedAt": "2026-02-01T07:23:33.961Z",
            "isEstimated": true,
            "estimationMethod": "ESTIMATED_GENERAL_PURPOSE_ZONE_MODEL",
            "value": 53555420
        },
        {
            "datetime": "2023-10-01T00:00:00.000Z",
            "updatedAt": "2026-01-27T14:56:56.024Z",
            "isEstimated": true,
            "estimationMethod": "ESTIMATED_GENERAL_PURPOSE_ZONE_MODEL",
            "value": 53552820
        },
        {
            "datetime": "2023-11-01T00:00:00.000Z",
            "updatedAt": "2026-01-27T14:56:56.024Z",
            "isEstimated": true,
            "estimationMethod": "ESTIMATED_GENERAL_PURPOSE_ZONE_MODEL",
            "value": 49774024
        },
        {
            "datetime": "2023-12-01T00:00:00.000Z",
            "updatedAt": "2026-01-27T14:56:56.024Z",
            "isEstimated": true,
            "estimationMethod": "ESTIMATED_GENERAL_PURPOSE_ZONE_MODEL",
            "value": 43896184
        }
    ],
    "source": "solar",
    "aggregationPeriod": "monthly"
}