{
    "zone": "PT-MA",
    "temporalGranularity": "monthly",
    "unit": "MWh",
    "data": [
        {
            "datetime": "2023-01-01T00:00:00.000Z",
            "updatedAt": "2026-02-07T15:44:52.673Z",
            "isEstimated": true,
            "estimationMethod": "ESTIMATED_GENERAL_PURPOSE_ZONE_MODEL",
            "value": 41272
        },
        {
            "datetime": "2023-02-01T00:00:00.000Z",
            "updatedAt": "2026-01-27T14:56:56.024Z",
            "isEstimated": true,
            "estimationMethod": "ESTIMATED_GENERAL_PURPOSE_ZONE_MODEL",
            "value": 34253
        },
        {
            "datetime": "2023-03-01T00:00:00.000Z",
            "updatedAt": "2026-01-27T14:56:56.024Z",
            "isEstimated": true,
            "estimationMethod": "ESTIMATED_GENERAL_PURPOSE_ZONE_MODEL",
            "value": 47745
        },
        {
            "datetime": "2023-04-01T00:00:00.000Z",
            "updatedAt": "2026-01-27T14:56:56.024Z",
            "isEstimated": true,
            "estimationMethod": "ESTIMATED_GENERAL_PURPOSE_ZONE_MODEL",
            "value": 46597
        },
        {
            "datetime": "2023-05-01T00:00:00.000Z",
            "updatedAt": "2026-01-27T14:56:56.024Z",
            "isEstimated": true,
            "estimationMethod": "ESTIMATED_GENERAL_PURPOSE_ZONE_MODEL",
            "value": 36072
        },
        {
            "datetime": "2023-06-01T00:00:00.000Z",
            "updatedAt": "2026-01-27T14:56:56.024Z",
            "isEstimated": true,
            "estimationMethod": "ESTIMATED_GENERAL_PURPOSE_ZONE_MODEL",
            "value": 33708
        },
        {
            "datetime": "2023-07-01T00:00:00.000Z",
            "updatedAt": "2026-01-27T14:56:56.024Z",
            "isEstimated": true,
            "estimationMethod": "ESTIMATED_GENERAL_PURPOSE_ZONE_MODEL",
            "value": 45446
        },
        {
            "datetime": "2023-08-01T00:00:00.000Z",
            "updatedAt": "2026-01-27T14:56:56.024Z",
            "isEstimated": true,
            "estimationMethod": "ESTIMATED_GENERAL_PURPOSE_ZONE_MODEL",
            "value": 53800
        },
        {
            "datetime": "2023-09-01T00:00:00.000Z",
            "updatedAt": "2026-01-27T14:56:56.024Z",
            "isEstimated": true,
            "estimationMethod": "ESTIMATED_GENERAL_PURPOSE_ZONE_MODEL",
            "value": 44397
        },
        {
            "datetime": "2023-10-01T00:00:00.000Z",
            "updatedAt": "2026-01-27T14:56:56.024Z",
            "isEstimated": true,
            "estimationMethod": "ESTIMATED_GENERAL_PURPOSE_ZONE_MODEL",
            "value": 49529
        },
        {
            "datetime": "2023-11-01T00:00:00.000Z",
            "updatedAt": "2026-01-27T14:56:56.024Z",
            "isEstimated": true,
            "estimationMethod": "ESTIMATED_GENERAL_PURPOSE_ZONE_MODEL",
            "value": 46585
        },
        {
            "datetime": "2023-12-01T00:00:00.000Z",
            "updatedAt": "2026-01-27T14:56:56.024Z",
            "isEstimated": true,
            "estimationMethod": "ESTIMATED_GENERAL_PURPOSE_ZONE_MODEL",
            "value": 39230
        }
    ],
    "source": "oil",
    "aggregationPeriod": "monthly"
}