{
    "zone": "NO",
    "temporalGranularity": "monthly",
    "unit": "MWh",
    "data": [
        {
            "datetime": "2021-01-01T00:00:00.000Z",
            "updatedAt": "2026-02-07T23:04:42.039Z",
            "estimationMethod": "MEASURED",
            "value": 27
        },
        {
            "datetime": "2021-02-01T00:00:00.000Z",
            "updatedAt": "2026-02-01T07:23:45.030Z",
            "estimationMethod": "MEASURED",
            "value": 69
        },
        {
            "datetime": "2021-03-01T00:00:00.000Z",
            "updatedAt": "2026-02-01T07:23:45.030Z",
            "estimationMethod": "MEASURED",
            "value": 65
        },
        {
            "datetime": "2021-04-01T00:00:00.000Z",
            "updatedAt": "2026-02-01T07:23:45.030Z",
            "estimationMethod": "MEASURED",
            "value": 41
        },
        {
            "datetime": "2021-05-01T00:00:00.000Z",
            "updatedAt": "2026-02-01T07:23:45.030Z",
            "estimationMethod": "MEASURED",
            "value": 78
        },
        {
            "datetime": "2021-06-01T00:00:00.000Z",
            "updatedAt": "2026-02-01T07:23:45.030Z",
            "estimationMethod": "MEASURED",
            "value": 10
        },
        {
            "datetime": "2021-07-01T00:00:00.000Z",
            "updatedAt": "2026-02-01T07:23:45.030Z",
            "estimationMethod": "MEASURED",
            "value": 11
        },
        {
            "datetime": "2021-08-01T00:00:00.000Z",
            "updatedAt": "2026-02-01T07:23:45.030Z",
            "estimationMethod": "MEASURED",
            "value": 43
        },
        {
            "datetime": "2021-09-01T00:00:00.000Z",
            "updatedAt": "2026-02-01T07:23:45.030Z",
            "estimationMethod": "MEASURED",
            "value": 14
        },
        {
            "datetime": "2021-10-01T00:00:00.000Z",
            "updatedAt": "2026-02-01T07:23:45.030Z",
            "estimationMethod": "MEASURED",
            "value": 60
        },
        {
            "datetime": "2021-11-01T00:00:00.000Z",
            "updatedAt": "2026-02-01T07:23:45.030Z",
            "estimationMethod": "MEASURED",
            "value": 36
        },
        {
            "datetime": "2021-12-01T00:00:00.000Z",
            "updatedAt": "2026-02-01T07:23:45.030Z",
            "estimationMethod": "MEASURED",
            "value": 112
        }
    ],
    "source": "geothermal",
    "aggregationPeriod": "monthly"
}