{
    "zone": "JP-HR",
    "temporalGranularity": "monthly",
    "unit": "MWh",
    "data": [
        {
            "datetime": "2021-01-01T00:00:00.000Z",
            "updatedAt": "2026-02-07T23:04:42.039Z",
            "isEstimated": true,
            "estimationMethod": "ESTIMATED_MODE_BREAKDOWN",
            "value": 939966
        },
        {
            "datetime": "2021-02-01T00:00:00.000Z",
            "updatedAt": "2026-01-27T15:37:43.126Z",
            "isEstimated": true,
            "estimationMethod": "ESTIMATED_MODE_BREAKDOWN",
            "value": 798419
        },
        {
            "datetime": "2021-03-01T00:00:00.000Z",
            "updatedAt": "2026-01-27T15:37:43.126Z",
            "isEstimated": true,
            "estimationMethod": "ESTIMATED_MODE_BREAKDOWN",
            "value": 770005
        },
        {
            "datetime": "2021-04-01T00:00:00.000Z",
            "updatedAt": "2026-01-27T15:37:43.126Z",
            "isEstimated": true,
            "estimationMethod": "ESTIMATED_MODE_BREAKDOWN",
            "value": 654885
        },
        {
            "datetime": "2021-05-01T00:00:00.000Z",
            "updatedAt": "2026-01-27T15:37:43.126Z",
            "isEstimated": true,
            "estimationMethod": "ESTIMATED_MODE_BREAKDOWN",
            "value": 615076
        },
        {
            "datetime": "2021-06-01T00:00:00.000Z",
            "updatedAt": "2026-01-27T15:37:43.126Z",
            "isEstimated": true,
            "estimationMethod": "ESTIMATED_MODE_BREAKDOWN",
            "value": 639220
        },
        {
            "datetime": "2021-07-01T00:00:00.000Z",
            "updatedAt": "2026-01-27T15:37:43.126Z",
            "isEstimated": true,
            "estimationMethod": "ESTIMATED_MODE_BREAKDOWN",
            "value": 758540
        },
        {
            "datetime": "2021-08-01T00:00:00.000Z",
            "updatedAt": "2026-01-27T15:37:43.126Z",
            "isEstimated": true,
            "estimationMethod": "ESTIMATED_MODE_BREAKDOWN",
            "value": 748073
        },
        {
            "datetime": "2021-09-01T00:00:00.000Z",
            "updatedAt": "2026-01-27T15:37:43.126Z",
            "isEstimated": true,
            "estimationMethod": "ESTIMATED_MODE_BREAKDOWN",
            "value": 676155
        },
        {
            "datetime": "2021-10-01T00:00:00.000Z",
            "updatedAt": "2026-01-27T15:37:43.126Z",
            "isEstimated": true,
            "estimationMethod": "ESTIMATED_MODE_BREAKDOWN",
            "value": 671117
        },
        {
            "datetime": "2021-11-01T00:00:00.000Z",
            "updatedAt": "2026-01-27T15:37:43.126Z",
            "isEstimated": true,
            "estimationMethod": "ESTIMATED_MODE_BREAKDOWN",
            "value": 712686
        },
        {
            "datetime": "2021-12-01T00:00:00.000Z",
            "updatedAt": "2026-01-27T15:37:43.126Z",
            "isEstimated": true,
            "estimationMethod": "ESTIMATED_MODE_BREAKDOWN",
            "value": 866504
        }
    ],
    "source": "coal",
    "aggregationPeriod": "monthly"
}