{
    "zone": "SE",
    "temporalGranularity": "monthly",
    "unit": "MWh",
    "data": [
        {
            "datetime": "2023-01-01T00:00:00.000Z",
            "updatedAt": "2026-02-09T20:20:37.719Z",
            "estimationMethod": "MEASURED",
            "value": 32119
        },
        {
            "datetime": "2023-02-01T00:00:00.000Z",
            "updatedAt": "2026-02-01T07:23:33.961Z",
            "estimationMethod": "MEASURED",
            "value": 11896
        },
        {
            "datetime": "2023-03-01T00:00:00.000Z",
            "updatedAt": "2026-02-09T20:20:37.719Z",
            "estimationMethod": "MEASURED",
            "value": 31643
        },
        {
            "datetime": "2023-04-01T00:00:00.000Z",
            "updatedAt": "2026-02-01T07:23:33.961Z",
            "estimationMethod": "MEASURED",
            "value": 19650
        },
        {
            "datetime": "2023-05-01T00:00:00.000Z",
            "updatedAt": "2026-02-01T07:23:33.961Z",
            "estimationMethod": "MEASURED",
            "value": 20651
        },
        {
            "datetime": "2023-06-01T00:00:00.000Z",
            "updatedAt": "2026-02-01T07:23:33.961Z",
            "estimationMethod": "MEASURED",
            "value": 9003
        },
        {
            "datetime": "2023-07-01T00:00:00.000Z",
            "updatedAt": "2026-02-01T07:23:33.961Z",
            "estimationMethod": "MEASURED",
            "value": 9928
        },
        {
            "datetime": "2023-08-01T00:00:00.000Z",
            "updatedAt": "2026-02-01T07:23:33.961Z",
            "estimationMethod": "MEASURED",
            "value": 8230
        },
        {
            "datetime": "2023-09-01T00:00:00.000Z",
            "updatedAt": "2026-02-01T07:23:33.961Z",
            "estimationMethod": "MEASURED",
            "value": 7185
        },
        {
            "datetime": "2023-10-01T00:00:00.000Z",
            "updatedAt": "2026-02-09T20:20:37.719Z",
            "estimationMethod": "MEASURED",
            "value": 6506
        },
        {
            "datetime": "2023-11-01T00:00:00.000Z",
            "updatedAt": "2026-02-01T07:23:33.961Z",
            "estimationMethod": "MEASURED",
            "value": 18812
        },
        {
            "datetime": "2023-12-01T00:00:00.000Z",
            "updatedAt": "2026-02-09T20:20:37.719Z",
            "estimationMethod": "MEASURED",
            "value": 66934
        }
    ],
    "source": "biomass",
    "aggregationPeriod": "monthly"
}