{
    "zone": "JO",
    "temporalGranularity": "monthly",
    "unit": "MWh",
    "data": [
        {
            "datetime": "2022-01-01T00:00:00.000Z",
            "updatedAt": "2026-02-07T23:00:25.543Z",
            "isEstimated": true,
            "estimationMethod": "ESTIMATED_GENERAL_PURPOSE_ZONE_MODEL",
            "value": 152514
        },
        {
            "datetime": "2022-02-01T00:00:00.000Z",
            "updatedAt": "2026-01-27T15:25:10.819Z",
            "isEstimated": true,
            "estimationMethod": "ESTIMATED_GENERAL_PURPOSE_ZONE_MODEL",
            "value": 124139
        },
        {
            "datetime": "2022-03-01T00:00:00.000Z",
            "updatedAt": "2026-01-27T15:25:10.819Z",
            "isEstimated": true,
            "estimationMethod": "ESTIMATED_GENERAL_PURPOSE_ZONE_MODEL",
            "value": 170371
        },
        {
            "datetime": "2022-04-01T00:00:00.000Z",
            "updatedAt": "2026-01-27T15:25:10.819Z",
            "isEstimated": true,
            "estimationMethod": "ESTIMATED_GENERAL_PURPOSE_ZONE_MODEL",
            "value": 141808
        },
        {
            "datetime": "2022-05-01T00:00:00.000Z",
            "updatedAt": "2026-01-27T15:25:10.819Z",
            "isEstimated": true,
            "estimationMethod": "ESTIMATED_GENERAL_PURPOSE_ZONE_MODEL",
            "value": 166873
        },
        {
            "datetime": "2022-06-01T00:00:00.000Z",
            "updatedAt": "2026-01-27T15:25:10.819Z",
            "isEstimated": true,
            "estimationMethod": "ESTIMATED_GENERAL_PURPOSE_ZONE_MODEL",
            "value": 144493
        },
        {
            "datetime": "2022-07-01T00:00:00.000Z",
            "updatedAt": "2026-01-27T15:25:10.819Z",
            "isEstimated": true,
            "estimationMethod": "ESTIMATED_GENERAL_PURPOSE_ZONE_MODEL",
            "value": 162185
        },
        {
            "datetime": "2022-08-01T00:00:00.000Z",
            "updatedAt": "2026-01-27T15:25:10.819Z",
            "isEstimated": true,
            "estimationMethod": "ESTIMATED_GENERAL_PURPOSE_ZONE_MODEL",
            "value": 151652
        },
        {
            "datetime": "2022-09-01T00:00:00.000Z",
            "updatedAt": "2026-01-27T15:25:10.819Z",
            "isEstimated": true,
            "estimationMethod": "ESTIMATED_GENERAL_PURPOSE_ZONE_MODEL",
            "value": 135347
        },
        {
            "datetime": "2022-10-01T00:00:00.000Z",
            "updatedAt": "2026-01-27T15:25:10.819Z",
            "isEstimated": true,
            "estimationMethod": "ESTIMATED_GENERAL_PURPOSE_ZONE_MODEL",
            "value": 127604
        },
        {
            "datetime": "2022-11-01T00:00:00.000Z",
            "updatedAt": "2026-01-27T15:25:10.819Z",
            "isEstimated": true,
            "estimationMethod": "ESTIMATED_GENERAL_PURPOSE_ZONE_MODEL",
            "value": 122831
        },
        {
            "datetime": "2022-12-01T00:00:00.000Z",
            "updatedAt": "2026-01-27T15:25:10.819Z",
            "isEstimated": true,
            "estimationMethod": "ESTIMATED_GENERAL_PURPOSE_ZONE_MODEL",
            "value": 148167
        }
    ],
    "source": "wind",
    "aggregationPeriod": "monthly"
}