{
    "zone": "US-AK",
    "temporalGranularity": "monthly",
    "unit": "MWh",
    "data": [
        {
            "datetime": "2022-01-01T00:00:00.000Z",
            "updatedAt": "2026-02-07T23:00:25.543Z",
            "isEstimated": true,
            "estimationMethod": "ESTIMATED_GENERAL_PURPOSE_ZONE_MODEL",
            "value": 19614
        },
        {
            "datetime": "2022-02-01T00:00:00.000Z",
            "updatedAt": "2026-01-27T15:25:10.819Z",
            "isEstimated": true,
            "estimationMethod": "ESTIMATED_GENERAL_PURPOSE_ZONE_MODEL",
            "value": 16454
        },
        {
            "datetime": "2022-03-01T00:00:00.000Z",
            "updatedAt": "2026-01-27T15:25:10.819Z",
            "isEstimated": true,
            "estimationMethod": "ESTIMATED_GENERAL_PURPOSE_ZONE_MODEL",
            "value": 14602
        },
        {
            "datetime": "2022-04-01T00:00:00.000Z",
            "updatedAt": "2026-01-27T15:25:10.819Z",
            "isEstimated": true,
            "estimationMethod": "ESTIMATED_GENERAL_PURPOSE_ZONE_MODEL",
            "value": 9650
        },
        {
            "datetime": "2022-05-01T00:00:00.000Z",
            "updatedAt": "2026-01-27T15:25:10.819Z",
            "isEstimated": true,
            "estimationMethod": "ESTIMATED_GENERAL_PURPOSE_ZONE_MODEL",
            "value": 5833
        },
        {
            "datetime": "2022-06-01T00:00:00.000Z",
            "updatedAt": "2026-01-27T15:25:10.819Z",
            "isEstimated": true,
            "estimationMethod": "ESTIMATED_GENERAL_PURPOSE_ZONE_MODEL",
            "value": 3409
        },
        {
            "datetime": "2022-07-01T00:00:00.000Z",
            "updatedAt": "2026-01-27T15:25:10.819Z",
            "isEstimated": true,
            "estimationMethod": "ESTIMATED_GENERAL_PURPOSE_ZONE_MODEL",
            "value": 3370
        },
        {
            "datetime": "2022-08-01T00:00:00.000Z",
            "updatedAt": "2026-01-27T15:25:10.819Z",
            "isEstimated": true,
            "estimationMethod": "ESTIMATED_GENERAL_PURPOSE_ZONE_MODEL",
            "value": 5337
        },
        {
            "datetime": "2022-09-01T00:00:00.000Z",
            "updatedAt": "2026-01-27T15:25:10.819Z",
            "isEstimated": true,
            "estimationMethod": "ESTIMATED_GENERAL_PURPOSE_ZONE_MODEL",
            "value": 8966
        },
        {
            "datetime": "2022-10-01T00:00:00.000Z",
            "updatedAt": "2026-01-27T15:25:10.819Z",
            "isEstimated": true,
            "estimationMethod": "ESTIMATED_GENERAL_PURPOSE_ZONE_MODEL",
            "value": 14070
        },
        {
            "datetime": "2022-11-01T00:00:00.000Z",
            "updatedAt": "2026-01-27T15:25:10.819Z",
            "isEstimated": true,
            "estimationMethod": "ESTIMATED_GENERAL_PURPOSE_ZONE_MODEL",
            "value": 17641
        },
        {
            "datetime": "2022-12-01T00:00:00.000Z",
            "updatedAt": "2026-01-27T15:25:10.819Z",
            "isEstimated": true,
            "estimationMethod": "ESTIMATED_GENERAL_PURPOSE_ZONE_MODEL",
            "value": 20326
        }
    ],
    "source": "wind",
    "aggregationPeriod": "monthly"
}